megarnucleusx13/__init__.py
megarnucleusx13/megan.py
megarnucleusx13/megan_beta.py
megarnucleusx13-0.0.2.dist-info/METADATA
megarnucleusx13-0.0.2.dist-info/WHEEL
megarnucleusx13-0.0.2.dist-info/entry_points.txt
megarnucleusx13-0.0.2.dist-info/top_level.txt
megarnucleusx13-0.0.2.dist-info/RECORD
