Metadata-Version: 2.4
Name: megarnucleusx13
Version: 0.0.2
Summary: MeganR Nucleus X13 - Mini IA en Python
Author: luia
Requires-Dist: numpy
Dynamic: author
Dynamic: requires-dist
Dynamic: summary
